websitegen/__init__.py
websitegen/main.py
websitegen/rss_feed.xml
websitegen/rss_item.xml
websitegen/themes/clean/info.txt
websitegen/themes/clean/style.css
websitegen/themes/clean/template.html
websitegen/themes/clean-with-edit/info.txt
websitegen/themes/clean-with-edit/style.css
websitegen/themes/clean-with-edit/template.html
websitegen/themes/fancy/info.txt
websitegen/themes/fancy/style.css
websitegen/themes/fancy/template.html
websitegen/themes/side-nav/favicon.png
websitegen/themes/side-nav/info.txt
websitegen/themes/side-nav/style.css
websitegen/themes/side-nav/template.html
websitegen/themes/side-nav-with-edit/favicon.png
websitegen/themes/side-nav-with-edit/info.txt
websitegen/themes/side-nav-with-edit/style.css
websitegen/themes/side-nav-with-edit/template.html
websitegen/themes/side-nav-with-edit-and-auto-gen-menu/favicon.png
websitegen/themes/side-nav-with-edit-and-auto-gen-menu/info.txt
websitegen/themes/side-nav-with-edit-and-auto-gen-menu/style.css
websitegen/themes/side-nav-with-edit-and-auto-gen-menu/template.html
websitegen/themes/top-nav/favicon.png
websitegen/themes/top-nav/style.css
websitegen/themes/top-nav/template.html
website_generator-1.0.0a18.dist-info/LICENSE
website_generator-1.0.0a18.dist-info/METADATA
website_generator-1.0.0a18.dist-info/WHEEL
website_generator-1.0.0a18.dist-info/entry_points.txt
website_generator-1.0.0a18.dist-info/top_level.txt
website_generator-1.0.0a18.dist-info/RECORD
