Metadata-Version: 2.1
Name: website-generator
Version: 1.0.0a18
Summary: A minimalistic static website generator
Home-page: https://gitlab.com/SunyataZero/website-generator
Author: Tord Dellsén
Author-email: tord.dellsen@gmail.com
License: GPLv3
Platform: UNKNOWN
Classifier: License :: OSI Approved :: GNU General Public License v3 (GPLv3)
Classifier: Programming Language :: Python
Classifier: Programming Language :: Python :: 3
Classifier: Development Status :: 2 - Pre-Alpha
Requires-Python: >=3.9
License-File: LICENSE
Requires-Dist: mistletoe (>=0.7.2)
